[{"pk": 2004, "model": "app.toques", "fields": {"acao": 1, "t": 410, "jogo": 29, "y": 544, "x": 74}}, {"pk": 2005, "model": "app.toques", "fields": {"acao": 1, "t": 436, "jogo": 29, "y": 559, "x": 72}}, {"pk": 2006, "model": "app.toques", "fields": {"acao": 3, "t": 836, "jogo": 29, "y": 404, "x": 67}}, {"pk": 2007, "model": "app.toques", "fields": {"acao": 1, "t": 971, "jogo": 29, "y": 568, "x": 81}}, {"pk": 2008, "model": "app.toques", "fields": {"acao": 1, "t": 1002, "jogo": 29, "y": 555, "x": 83}}, {"pk": 2009, "model": "app.toques", "fields": {"acao": 2, "t": 1061, "jogo": 29, "y": 466, "x": 79}}, {"pk": 2010, "model": "app.toques", "fields": {"acao": 9, "t": 1154, "jogo": 29, "y": 41, "x": 470}}, {"pk": 2011, "model": "app.toques", "fields": {"acao": 1, "t": 1502, "jogo": 29, "y": 555, "x": 89}}, {"pk": 2012, "model": "app.toques", "fields": {"acao": 1, "t": 1524, "jogo": 29, "y": 566, "x": 83}}, {"pk": 2013, "model": "app.toques", "fields": {"acao": 3, "t": 2316, "jogo": 29, "y": 404, "x": 94}}, {"pk": 2014, "model": "app.toques", "fields": {"acao": 1, "t": 2408, "jogo": 29, "y": 563, "x": 100}}, {"pk": 2015, "model": "app.toques", "fields": {"acao": 1, "t": 2426, "jogo": 29, "y": 561, "x": 98}}, {"pk": 2016, "model": "app.toques", "fields": {"acao": 1, "t": 2440, "jogo": 29, "y": 559, "x": 94}}, {"pk": 2017, "model": "app.toques", "fields": {"acao": 2, "t": 2678, "jogo": 29, "y": 480, "x": 74}}, {"pk": 2018, "model": "app.toques", "fields": {"acao": 1, "t": 2831, "jogo": 29, "y": 556, "x": 61}}, {"pk": 2019, "model": "app.toques", "fields": {"acao": 1, "t": 2913, "jogo": 29, "y": 558, "x": 84}}, {"pk": 2020, "model": "app.toques", "fields": {"acao": 10, "t": 3272, "jogo": 29, "y": 55, "x": 697}}, {"pk": 2021, "model": "app.toques", "fields": {"acao": 1, "t": 3369, "jogo": 29, "y": 549, "x": 90}}, {"pk": 2022, "model": "app.toques", "fields": {"acao": 1, "t": 3390, "jogo": 29, "y": 559, "x": 88}}, {"pk": 2023, "model": "app.toques", "fields": {"acao": 3, "t": 3472, "jogo": 29, "y": 402, "x": 93}}, {"pk": 2024, "model": "app.toques", "fields": {"acao": 1, "t": 3555, "jogo": 29, "y": 563, "x": 60}}, {"pk": 2025, "model": "app.toques", "fields": {"acao": 1, "t": 3580, "jogo": 29, "y": 556, "x": 70}}, {"pk": 2026, "model": "app.toques", "fields": {"acao": 2, "t": 4077, "jogo": 29, "y": 486, "x": 84}}, {"pk": 2027, "model": "app.toques", "fields": {"acao": 1, "t": 4177, "jogo": 29, "y": 557, "x": 89}}, {"pk": 2028, "model": "app.toques", "fields": {"acao": 9, "t": 4267, "jogo": 29, "y": 54, "x": 484}}]